{
  "org": "$HZN_ORG_ID",
  "label": "Location2wiotp direct service pattern for $ARCH",
  "description": "Horizon deployment pattern that runs the location2wiotp service to send the edge node GPS info without core-iot",
  "public": true,
  "services": [
    {
      "serviceUrl": "https://github.com/open-horizon/examples/wiki/service-location2wiotp-no-core-iot",
      "serviceOrgid": "$HZN_ORG_ID",
      "serviceArch": "$ARCH",
      "serviceVersions": [
        {
          "version": "$VERSION",
          "deployment_overrides": null,
          "deployment_overrides_signature": "",
          "priority": {},
          "upgradePolicy": {}
        }
      ],
      "nodeHealth": {
        "missing_heartbeat_interval": 600,
        "check_agreement_status": 120
      }
    }
  ],
  "agreementProtocols": [
    {
      "name": "Basic"
    }
  ]
}
